{
  "entries": {
    "Hanjo|4CCFader": "",
    "JulesV|giro": "",
    "MentalSandal|nice-tapes": "",
    "Midworld|sweet bees": "",
    "NightMachines|nmQuadroDubber": "",
    "P1505|orbital": "",
    "RGB|intervaltrainer": "",
    "WilliamHazard|shnthsalslied": "https://www.youtube.com/watch?v=T5zg_Nl8zuI",
    "adamstaff|metronome": "",
    "alanza|choukanzu": "",
    "andrew|iiitoii": "",
    "andy|hpns": "",
    "crim|norman": "",
    "csboling|folio": "",
    "csboling|foundry": "",
    "deeg_deeg_deeg|noize": "https://www.youtube.com/watch?v=bCr1xxfevpc",
    "duncangeere|ppm_norns": "",
    "eigen|3d": "",
    "eigen|p8": "",
    "emanuelep|dimension-expander": "",
    "emanuelep|time-rhythm": "",
    "frederickk|kreislauf": "",
    "imminent_gloom|form!matter": "",
    "imminent_gloom|støv": "",
    "infinitedigits|warmreload": "",
    "jah|moln": "",
    "jah|step": "https://www.youtube.com/watch?v=pI81ISvjST4",
    "jaseknighter|clipper": "",
    "jaseknighter|parrot": "",
    "jaseknighter|semiconductor": "",
    "jlmitch5|n16o": "",
    "justmat|crow_talk": "",
    "justmat|sam": "",
    "kjames|descartes": "",
    "kurogedelic|avonlea": "",
    "lylem|seaflex": "",
    "markeats|tuner": "",
    "midouest|bitebeet": "",
    "midouest|just-play": "",
    "mimetaur|arcify": "",
    "mimetaur|onehanded": "https://www.youtube.com/watch?v=oBKVeXLxXF4",
    "nattog|awake-passersby": "https://www.youtube.com/watch?v=BYjTCWS-B7o",
    "nattog|passthrough": "",
    "niksilver|clockabout": "",
    "niksilver|midi-review": "",
    "notester|lemniscate": "",
    "notester|magpie": "",
    "okyeron|clarck": "",
    "pangrus|automs70": "",
    "pangrus|hachi": "",
    "sonoCircuit|midiplayer": "",
    "stvnrlly|oblique": "",
    "synthetiv|caliper": "",
    "tehn|blue": "https://www.youtube.com/watch?v=frNbtfMnP20",
    "toomanatees|raft": "",
    "trentgill|bowering": "",
    "tyleretters|splicer": "https://www.youtube.com/watch?v=kaH6qetN0fE",
    "tyleretters|u": "",
    "wardores|cryptkeeper": "",
    "yota|interpret": "",
    "zebra|thebangs": ""
  },
  "signature": "v1-strict-norns-required"
}